<?xml version="1.0" encoding="ISO-8859-1"?>
<meses>
  <mes>
    <idmes>1</idmes>
    <nombre>Enero</nombre>
    <faltas>2</faltas>
  </mes>
  <mes>
    <idmes>2</idmes>
    <nombre>Febrero</nombre>
    <faltas>1</faltas>
  </mes>
  <mes>
    <idmes>3</idmes>
    <nombre>Marzo</nombre>
    <faltas>3</faltas>
  </mes>
  <mes>
    <idmes>4</idmes>
    <nombre>Abril</nombre>
    <faltas>2</faltas>
  </mes>
  <mes>
    <idmes>5</idmes>
    <nombre>Mayo</nombre>
    <faltas>3</faltas>
  </mes>
  <mes>
    <idmes>6</idmes>
    <nombre>Junio</nombre>
    <faltas>1</faltas>
  </mes>
  <mes>
    <idmes>9</idmes>
    <nombre>Septiembre</nombre>
    <faltas>2</faltas>
  </mes>
  <mes>
    <idmes>10</idmes>
    <nombre>Octubre</nombre>
    <faltas>3</faltas>
  </mes>
  <mes>
    <idmes>11</idmes>
    <nombre>Noviembre</nombre>
    <faltas>3</faltas>
  </mes>
  <mes>
    <idmes>12</idmes>
    <nombre>Diciembre</nombre>
    <faltas>2</faltas>
  </mes>
</meses>
